primefaster/__init__.py
primefaster/primefaster.py
prime_faster-0.0.9.dist-info/LICENSE
prime_faster-0.0.9.dist-info/METADATA
prime_faster-0.0.9.dist-info/WHEEL
prime_faster-0.0.9.dist-info/top_level.txt
prime_faster-0.0.9.dist-info/RECORD
