Metadata-Version: 2.1
Name: prime-faster
Version: 0.0.9
Summary: prime-faster - Faster Prime Number Generator
Home-page: https://github.com/takahashi-akari/prime-faster
Author: Takahashi Akari
Author-email: akaritakahashioss@gmail.com
Classifier: Programming Language :: Python :: 3
Classifier: License :: OSI Approved :: MIT License
Classifier: Operating System :: OS Independent
Requires-Python: >=3.6
License-File: LICENSE
